{
  "main": {
    "id": "5324373015726ba8",
    "type": "split",
    "children": [
      {
        "id": "23717b1e609790ef",
        "type": "tabs",
        "children": [
          {
            "id": "3f11fda852782ac5",
            "type": "leaf",
            "state": {
              "type": "empty",
              "state": {},
              "icon": "lucide-file",
              "title": "Nueva pestaña"
            }
          }
        ]
      }
    ],
    "direction": "vertical"
  },
  "left": {
    "id": "ebc4e65dbac994d4",
    "type": "split",
    "children": [
      {
        "id": "40f0c001c8d0b6fa",
        "type": "tabs",
        "children": [
          {
            "id": "0fbfb79084b3543f",
            "type": "leaf",
            "state": {
              "type": "empty",
              "state": {},
              "icon": "lucide-file",
              "title": "Nueva pestaña"
            }
          },
          {
            "id": "a49b85431644c5c5",
            "type": "leaf",
            "state": {
              "type": "search",
              "state": {
                "query": "",
                "matchingCase": false,
                "explainSearch": false,
                "collapseAll": false,
                "extraContext": false,
                "sortOrder": "alphabetical"
              },
              "icon": "lucide-search",
              "title": "Buscar"
            }
          },
          {
            "id": "309f8ae88dc744f5",
            "type": "leaf",
            "state": {
              "type": "bookmarks",
              "state": {},
              "icon": "lucide-bookmark",
              "title": "Marcadores"
            }
          },
          {
            "id": "929d48c17cbd7b3a",
            "type": "leaf",
            "state": {
              "type": "file-explorer",
              "state": {
                "sortOrder": "alphabetical",
                "autoReveal": false
              },
              "icon": "lucide-folder-closed",
              "title": "Explorador de archivos"
            }
          }
        ],
        "currentTab": 3
      }
    ],
    "direction": "horizontal",
    "width": 300
  },
  "right": {
    "id": "7d2adfc3e66f134a",
    "type": "split",
    "children": [
      {
        "id": "91e0393404b78e80",
        "type": "tabs",
        "children": [
          {
            "id": "5d5e07b8bfcdb17e",
            "type": "leaf",
            "state": {
              "type": "calendar",
              "state": {},
              "icon": "calendar-with-checkmark",
              "title": "Calendar"
            }
          },
          {
            "id": "14534c75d733a84e",
            "type": "leaf",
            "state": {
              "type": "pw.todo-list",
              "state": {},
              "icon": "lucide-ghost",
              "title": "pw.todo-list"
            }
          },
          {
            "id": "4b98c3c4de7736da",
            "type": "leaf",
            "state": {
              "type": "backlink",
              "state": {
                "file": "Pruebas/TODO/ToDo.md",
                "collapseAll": true,
                "extraContext": true,
                "sortOrder": "alphabetical",
                "showSearch": false,
                "searchQuery": "",
                "backlinkCollapsed": false,
                "unlinkedCollapsed": true
              },
              "icon": "links-coming-in",
              "title": "Enlaces entrantes de ToDo"
            }
          },
          {
            "id": "510432df1012debb",
            "type": "leaf",
            "state": {
              "type": "outgoing-link",
              "state": {
                "file": "Pruebas/TODO/ToDo.md",
                "linksCollapsed": false,
                "unlinkedCollapsed": true
              },
              "icon": "links-going-out",
              "title": "Enlaces salientes de ToDo"
            }
          },
          {
            "id": "4bde32c7aa67d48a",
            "type": "leaf",
            "state": {
              "type": "tag",
              "state": {
                "sortOrder": "frequency",
                "useHierarchy": true,
                "showSearch": false,
                "searchQuery": ""
              },
              "icon": "lucide-tags",
              "title": "Etiquetas"
            }
          },
          {
            "id": "b48eeb24a18fa9aa",
            "type": "leaf",
            "state": {
              "type": "outline",
              "state": {
                "file": "Aguacatec/Talleres/03 Tareas o TASK.md",
                "followCursor": true,
                "showSearch": false,
                "searchQuery": ""
              },
              "icon": "lucide-list",
              "title": "Esquema de 03 Tareas o TASK"
            }
          },
          {
            "id": "6f6a24fb1c008fe6",
            "type": "leaf",
            "state": {
              "type": "all-properties",
              "state": {
                "sortOrder": "frequency",
                "showSearch": false,
                "searchQuery": ""
              },
              "icon": "lucide-archive",
              "title": "Todas las propiedades"
            }
          },
          {
            "id": "b08bd79458ccdbea",
            "type": "leaf",
            "state": {
              "type": "file-properties",
              "state": {
                "file": "Recursos/favicon_lasCharlas.png"
              },
              "icon": "lucide-info",
              "title": "Propiedades de los archivos para favicon_lasCharlas"
            }
          },
          {
            "id": "9ee733cf39aa31b8",
            "type": "leaf",
            "state": {
              "type": "pw.todo-list",
              "state": {},
              "icon": "check-small",
              "title": "Todo"
            }
          }
        ]
      }
    ],
    "direction": "horizontal",
    "width": 282.5,
    "collapsed": true
  },
  "left-ribbon": {
    "hiddenItems": {
      "switcher:Abrir selector rápido": false,
      "graph:Abrir vista gráfica": false,
      "canvas:Crear nuevo lienzo": false,
      "daily-notes:Abrir la nota de hoy": false,
      "templates:Insertar plantilla": false,
      "command-palette:Abrir paleta de comandos": false,
      "bases:Crear nueva base": false,
      "zk-prefixer:Crear nueva nota única": false,
      "pexels-banner:🚩 Pixel Banner Menu": false,
      "digitalgarden:Digital Garden Publication Center": false,
      "templater-obsidian:Templater": false,
      "obsidian-excalidraw-plugin:Nuevo Bosquejo": false,
      "obsidian42-brat:BRAT": false,
      "homepage:Open homepage": false,
      "proletarian-wizard:Open planning": false,
      "slides-extended:Show slide preview": false
    }
  },
  "active": "3f11fda852782ac5",
  "lastOpenFiles": [
    "Notas diarias/06-10-2025.md",
    "README.md",
    "Clientes/Jordi amigo de Abel.md",
    "Telegram/photos/photo_1736181_18 - 20251006030054815.jpg",
    "Telegram/documents/NEXON_FLIXIP_Smarters - 20251006030225449.apk",
    "Telegram/documents/MarMontoriul - 20251006030130433.conf",
    "Telegram/documents",
    "Telegram/photos",
    "Telegram/Files",
    "Telegram/Pruebas - 20251006025753468.md",
    "Telegram/Hola - 20251006025722267.md",
    "Notas diarias/03-10-2025.md",
    "UPO/Sin título.md",
    "UPO/Gestion de dìas y Vacaciones.md",
    "UPO/Gestion de días y Vacaciones.md",
    "Aguacatec/Talleres/03 Tareas o TASK.md",
    "Notas diarias/29-09-2025.md",
    "Notas diarias/28-09-2025.md",
    "Notas diarias/01-10-2025.md",
    "Aguacatec/Talleres/00 Menù.md",
    "Aguacatec/Talleres/00 Menú.md",
    "00 Menú.md",
    "Dataview Tareas.md",
    "202509290406.md",
    "202509290407.md",
    "Sin título.base",
    "web clipper/Gu铆a Obsidian con sincronizaci贸n instant谩nea, gratuita y auto-hospedada.md",
    "UPO/Gestion de d锟斤拷as y Vacaciones.md (codificaci贸n no v谩lida)",
    "Tareas/Consultorias.md",
    "Tareas/Crear escaleta para Curso sobre notas y aplicaciones de notas.md",
    "Recursos/GTD.md",
    "Recursos/Método Zettelkasten.md",
    "Proxmox/Instalaci贸n Proxmox/Pasted image 20230309131845.png",
    "Proxmox/Instalaci贸n Proxmox/Pasted image 20230309132239.png",
    "Proxmox/Instalaci贸n Proxmox/Pasted image 20230309131417.png",
    "Proxmox/Instalaci贸n Proxmox/Pasted image 20230309124357.png",
    "Proxmox/Instalaci贸n Proxmox/Pasted image 20230309123832.png",
    "Proxmox/Instalaci贸n Proxmox/Pasted image 20230309133105.png",
    "Proxmox/Instalaci贸n Proxmox/Pasted image 20230309131103.png",
    "Proxmox/Instalaci贸n Proxmox/Pasted image 20230309133742.png",
    "Proxmox/Instalaci贸n Proxmox/Pasted image 20230309123715.png",
    "Proxmox/Instalaci贸n Proxmox",
    "Plantillas/{{date}}Horas UPO.md",
    "Plantillas/Plantilla cliente IPTV.md",
    "ObsidianGitSync/Clientes IPTV sync/Antonio Barrag锟斤拷n V锟斤拷zquez Compi Nacho.md (codificaci贸n no v谩lida)",
    "ObsidianGitSync/Clientes IPTV sync/XX-Tutorial instalaci锟斤拷n aplicaciones en Android.md (codificaci贸n no v谩lida)"
  ]
}